{"v":[{"w":[{"g":"Τοῦ Δαυιδ. Πρὸς σέ, κύριε, ἐκέκραξα, ὁ θεός μου, μὴ παρασιωπήσῃς ἀπ᾽ ἐμοῦ, μήποτε παρασιωπήσῃς ἀπ᾽ ἐμοῦ καὶ ὁμοιωθήσομαι τοῖς καταβαίνουσιν εἰς λάκκον.","h":"a/az Dávidé -hoz/-hez/-höz te Uram fölkiáltottam a/az Isten enyém ne hallgassál -tól/-től én nehogy hallgassál -tól/-től én és hasonlóvá leszek majd a/az leszállókhoz -ba/-be üreg","x":"a, az (használata általában mint a magyarban, de eltérés is van); ὁ μέν... ὁ δέ...: az egyik... a másik...; ὁ δέ az pedig, ő pedig <br>m/f/n.sg.nom.: ὁ, ἡ, τό <br>m/f/n.sg.acc.: τόν, τήν, τό <br>m/f/n.sg.gen.: τοῦ, τῆς, τοῦ <br>m/f/n.sg.dat.: τῷ, τῇ, τῷ<br>m/f/n.pl.nom.: οἱ, αἱ, τά <br>m/f/n.pl.acc.: τούς, τάς, τά <br>m/f/n.pl.gen.: τῶν, τῶν, τῶν<br>m/f/n.pl.dat.: τοῖς, ταῖς, τοῖς","i":"12102700100010","s":"Zsolt27,1","m":"m. sg. gen."},{"g":"Τοῦ","h":"a/az","x":"a, az (használata általában mint a magyarban, de eltérés is van); ὁ μέν... ὁ δέ...: az egyik... a másik...; ὁ δέ az pedig, ő pedig <br>m/f/n.sg.nom.: ὁ, ἡ, τό <br>m/f/n.sg.acc.: τόν, τήν, τό <br>m/f/n.sg.gen.: τοῦ, τῆς, τοῦ <br>m/f/n.sg.dat.: τῷ, τῇ, τῷ<br>m/f/n.pl.nom.: οἱ, αἱ, τά <br>m/f/n.pl.acc.: τούς, τάς, τά <br>m/f/n.pl.gen.: τῶν, τῶν, τῶν<br>m/f/n.pl.dat.: τοῖς, ταῖς, τοῖς","i":"12102700100010","s":"Zsolt27,1","m":"m. sg. gen."},{"g":"Δαυιδ.","h":"Dávidé","x":"Dávid; Δαυίδ írásmód: <abbr class='literature'>GNT27</abbr>; Δαυείδ írásmód: <abbr class='literature'>GNT_WH</abbr>","i":"12102700100020","s":"Zsolt27,1","m":"m. indecl."},{"g":"Πρὸς","h":"-hoz/-hez/-höz","x":"1. -hoz/-hez/-höz, felé, -ra/-re; 2. (a koinéban a παρά + dat. helyett) -nál/-nél","i":"12102700100030","s":"Zsolt27,1","m":"+ acc."},{"g":"σέ,","h":"te","x":"te; Ragozása:<br>sg.2.nom.: σύ (te)<br>sg.2.acc.: σέ v. σε (téged) <br>sg.2.gen.: σοῦ v. σου (tiéd)<br>sg.2.dat.: σοί v. σοι (neked)","i":"12102700100040","s":"Zsolt27,1","m":"sg. 2. acc."},{"g":"κύριε,","h":"Uram","x":"úr; Úr - A Septuagintában legtöbbször a négybetűs Istennév, a Tetragrammaton <span lang='he'>יהוה</span> helyettesítője","i":"12102700100050","s":"Zsolt27,1","m":"m. sg. voc."},{"g":"ἐκέκραξα,","h":"fölkiáltottam","x":"felkiált, kikiált","i":"12102700100060","s":"Zsolt27,1","m":"A. ind. aor. sg. 1."},{"g":"ὁ","h":"a/az","x":"a, az (használata általában mint a magyarban, de eltérés is van); ὁ μέν... ὁ δέ...: az egyik... a másik...; ὁ δέ az pedig, ő pedig <br>m/f/n.sg.nom.: ὁ, ἡ, τό <br>m/f/n.sg.acc.: τόν, τήν, τό <br>m/f/n.sg.gen.: τοῦ, τῆς, τοῦ <br>m/f/n.sg.dat.: τῷ, τῇ, τῷ<br>m/f/n.pl.nom.: οἱ, αἱ, τά <br>m/f/n.pl.acc.: τούς, τάς, τά <br>m/f/n.pl.gen.: τῶν, τῶν, τῶν<br>m/f/n.pl.dat.: τοῖς, ταῖς, τοῖς","i":"12102700100070","s":"Zsolt27,1","m":"m. sg. nom."},{"g":"θεός","h":"Isten","x":"Isten, isten","i":"12102700100080","s":"Zsolt27,1","m":"m. sg. nom."},{"g":"μου,","h":"enyém","x":"én; Ragozása: <br>sg.1.nom.: ἐγώ (én; <abbr class='literature'>ÚSzSz</abbr>: 1473); <br>sg.1.acc.: ἐμέ v. μέ (engem; <abbr class='literature'>ÚSzSz</abbr>: 1691);<br>sg.1.gen.: ἐμού v. μού (enyém; <abbr class='literature'>ÚSzSz</abbr>: 1700); <br>sg.1.dat.: ἐμοί v. μοί (nekem; <abbr class='literature'>ÚSzSz</abbr>: 1698)","i":"12102700100090","s":"Zsolt27,1","m":"sg. 1. gen."},{"g":"μὴ","h":"ne","x":"ne, nem; talán? ugye nem? A nem indicativusban álló igéket ill. igeneveket tagadja, míg az indicativus tagadására az οὐ, οὐκ, οὐχ használatos (<abbr class='literature'>BÚG</abbr> 22.1.); ου? μή: nagyon nem, semmiképpen nem","i":"12102700100100","s":"Zsolt27,1","m":""},{"g":"παρασιωπήσῃς","h":"hallgassál","x":"agyonhallgat vmit, nem említi","i":"12102700100110","s":"Zsolt27,1","m":"A. coni. aor. sg. 2."},{"g":"ἀπ᾽","h":"-tól/-től","x":"-tól/-től; -ból/-ből","i":"12102700100120","s":"Zsolt27,1","m":"+ gen."},{"g":"ἐμοῦ,","h":"én","x":"én; Ragozása: <br>sg.1.nom.: ἐγώ (én; <abbr class='literature'>ÚSzSz</abbr>: 1473); <br>sg.1.acc.: ἐμέ v. μέ (engem; <abbr class='literature'>ÚSzSz</abbr>: 1691);<br>sg.1.gen.: ἐμού v. μού (enyém; <abbr class='literature'>ÚSzSz</abbr>: 1700); <br>sg.1.dat.: ἐμοί v. μοί (nekem; <abbr class='literature'>ÚSzSz</abbr>: 1698)","i":"12102700100130","s":"Zsolt27,1","m":"sg. 1. gen."},{"g":"μήποτε","h":"nehogy","x":"nehogy; μήποτε írásmód: <abbr class='literature'>GNT27</abbr>; μή ποτε írásmód: <abbr class='literature'>GNT_WH</abbr>","i":"12102700100140","s":"Zsolt27,1","m":""},{"g":"παρασιωπήσῃς","h":"hallgassál","x":"agyonhallgat vmit, nem említi","i":"12102700100150","s":"Zsolt27,1","m":"A. coni. aor. sg. 2."},{"g":"ἀπ᾽","h":"-tól/-től","x":"-tól/-től; -ból/-ből","i":"12102700100160","s":"Zsolt27,1","m":"+ gen."},{"g":"ἐμοῦ","h":"én","x":"én; Ragozása: <br>sg.1.nom.: ἐγώ (én; <abbr class='literature'>ÚSzSz</abbr>: 1473); <br>sg.1.acc.: ἐμέ v. μέ (engem; <abbr class='literature'>ÚSzSz</abbr>: 1691);<br>sg.1.gen.: ἐμού v. μού (enyém; <abbr class='literature'>ÚSzSz</abbr>: 1700); <br>sg.1.dat.: ἐμοί v. μοί (nekem; <abbr class='literature'>ÚSzSz</abbr>: 1698)","i":"12102700100170","s":"Zsolt27,1","m":"sg. 1. gen."},{"g":"καὶ","h":"és","x":"és, is","i":"12102700100180","s":"Zsolt27,1","m":""},{"g":"ὁμοιωθήσομαι","h":"hasonlóvá leszek majd","x":"1. (A.) hasonlít; 2. (P.) hasonlóvá válik (akihez: + dat.)","i":"12102700100190","s":"Zsolt27,1","m":"P. fut. sg. 1."},{"g":"τοῖς","h":"a/az","x":"a, az (használata általában mint a magyarban, de eltérés is van); ὁ μέν... ὁ δέ...: az egyik... a másik...; ὁ δέ az pedig, ő pedig <br>m/f/n.sg.nom.: ὁ, ἡ, τό <br>m/f/n.sg.acc.: τόν, τήν, τό <br>m/f/n.sg.gen.: τοῦ, τῆς, τοῦ <br>m/f/n.sg.dat.: τῷ, τῇ, τῷ<br>m/f/n.pl.nom.: οἱ, αἱ, τά <br>m/f/n.pl.acc.: τούς, τάς, τά <br>m/f/n.pl.gen.: τῶν, τῶν, τῶν<br>m/f/n.pl.dat.: τοῖς, ταῖς, τοῖς","i":"12102700100200","s":"Zsolt27,1","m":"m. pl. dat."},{"g":"καταβαίνουσιν","h":"leszállókhoz","x":"1. lemegy, leszáll 2. (átv.) leereszkedik vmihez, belebocsátkozik vmibe","i":"12102700100210","s":"Zsolt27,1","m":"A. part. impf. m. pl. dat."},{"g":"εἰς","h":"-ba/-be","x":"-ba/-be, -ra/-re, ellen","i":"12102700100220","s":"Zsolt27,1","m":"+ acc."},{"g":"λάκκον.","h":"üreg","x":"1. lyuk; üreg; árok 2. vízmedence; ciszterna; medence (bor/olaj tárolására) 3. tó (vízi szárnyasok tenyésztésére)","i":"12102700100230","s":"Zsolt27,1","m":"m. sg. acc."}]},{"w":[{"g":"εἰσάκουσον τῆς φωνῆς τῆς δεήσεώς μου ἐν τῷ δέεσθαί με πρὸς σέ, ἐν τῷ με αἴρειν χεῖράς μου πρὸς ναὸν ἅγιόν σου.","h":"hallgasd meg a/az hangot a/az könyörgésé enyém -ban/-ben a/az kérni engem -hoz/-hez/-höz te -ban/-ben a/az én felemelni kezeket enyém felé templom szent tiéd","x":"1) (A) odafigyel, ráhallgat; 2) meghallgat, megért vmit; 3) (P) meghallgatásra talál","i":"12102700200010","s":"Zsolt27,2","m":"A. imprt. aor. sg. 2."},{"g":"εἰσάκουσον","h":"hallgasd meg","x":"1) (A) odafigyel, ráhallgat; 2) meghallgat, megért vmit; 3) (P) meghallgatásra talál","i":"12102700200010","s":"Zsolt27,2","m":"A. imprt. aor. sg. 2."},{"g":"τῆς","h":"a/az","x":"a, az (használata általában mint a magyarban, de eltérés is van); ὁ μέν... ὁ δέ...: az egyik... a másik...; ὁ δέ az pedig, ő pedig <br>m/f/n.sg.nom.: ὁ, ἡ, τό <br>m/f/n.sg.acc.: τόν, τήν, τό <br>m/f/n.sg.gen.: τοῦ, τῆς, τοῦ <br>m/f/n.sg.dat.: τῷ, τῇ, τῷ<br>m/f/n.pl.nom.: οἱ, αἱ, τά <br>m/f/n.pl.acc.: τούς, τάς, τά <br>m/f/n.pl.gen.: τῶν, τῶν, τῶν<br>m/f/n.pl.dat.: τοῖς, ταῖς, τοῖς","i":"12102700200020","s":"Zsolt27,2","m":"f. sg. gen."},{"g":"φωνῆς","h":"hangot","x":"hang","i":"12102700200030","s":"Zsolt27,2","m":"f. sg. gen."},{"g":"τῆς","h":"a/az","x":"a, az (használata általában mint a magyarban, de eltérés is van); ὁ μέν... ὁ δέ...: az egyik... a másik...; ὁ δέ az pedig, ő pedig <br>m/f/n.sg.nom.: ὁ, ἡ, τό <br>m/f/n.sg.acc.: τόν, τήν, τό <br>m/f/n.sg.gen.: τοῦ, τῆς, τοῦ <br>m/f/n.sg.dat.: τῷ, τῇ, τῷ<br>m/f/n.pl.nom.: οἱ, αἱ, τά <br>m/f/n.pl.acc.: τούς, τάς, τά <br>m/f/n.pl.gen.: τῶν, τῶν, τῶν<br>m/f/n.pl.dat.: τοῖς, ταῖς, τοῖς","i":"12102700200040","s":"Zsolt27,2","m":"f. sg. gen."},{"g":"δεήσεώς","h":"könyörgésé","x":"könyörgés","i":"12102700200050","s":"Zsolt27,2","m":"f. sg. gen."},{"g":"μου","h":"enyém","x":"én; Ragozása: <br>sg.1.nom.: ἐγώ (én; <abbr class='literature'>ÚSzSz</abbr>: 1473); <br>sg.1.acc.: ἐμέ v. μέ (engem; <abbr class='literature'>ÚSzSz</abbr>: 1691);<br>sg.1.gen.: ἐμού v. μού (enyém; <abbr class='literature'>ÚSzSz</abbr>: 1700); <br>sg.1.dat.: ἐμοί v. μοί (nekem; <abbr class='literature'>ÚSzSz</abbr>: 1698)","i":"12102700200060","s":"Zsolt27,2","m":"sg. 1. gen."},{"g":"ἐν","h":"-ban/-ben","x":"-ban, -ben; között; -val, -vel; által","i":"12102700200070","s":"Zsolt27,2","m":"+ dat."},{"g":"τῷ","h":"a/az","x":"a, az (használata általában mint a magyarban, de eltérés is van); ὁ μέν... ὁ δέ...: az egyik... a másik...; ὁ δέ az pedig, ő pedig <br>m/f/n.sg.nom.: ὁ, ἡ, τό <br>m/f/n.sg.acc.: τόν, τήν, τό <br>m/f/n.sg.gen.: τοῦ, τῆς, τοῦ <br>m/f/n.sg.dat.: τῷ, τῇ, τῷ<br>m/f/n.pl.nom.: οἱ, αἱ, τά <br>m/f/n.pl.acc.: τούς, τάς, τά <br>m/f/n.pl.gen.: τῶν, τῶν, τῶν<br>m/f/n.pl.dat.: τοῖς, ταῖς, τοῖς","i":"12102700200080","s":"Zsolt27,2","m":"n. sg. dat."},{"g":"δέεσθαί","h":"kérni","x":"kér, könyörög (akihez: + gen.)","i":"12102700200090","s":"Zsolt27,2","m":"M. inf. impf."},{"g":"με","h":"engem","x":"én; Ragozása: <br>sg.1.nom.: ἐγώ (én; <abbr class='literature'>ÚSzSz</abbr>: 1473); <br>sg.1.acc.: ἐμέ v. μέ (engem; <abbr class='literature'>ÚSzSz</abbr>: 1691);<br>sg.1.gen.: ἐμού v. μού (enyém; <abbr class='literature'>ÚSzSz</abbr>: 1700); <br>sg.1.dat.: ἐμοί v. μοί (nekem; <abbr class='literature'>ÚSzSz</abbr>: 1698)","i":"12102700200100","s":"Zsolt27,2","m":"sg. 1. acc."},{"g":"πρὸς","h":"-hoz/-hez/-höz","x":"1. -hoz/-hez/-höz, felé, -ra/-re; 2. (a koinéban a παρά + dat. helyett) -nál/-nél","i":"12102700200110","s":"Zsolt27,2","m":"+ acc."},{"g":"σέ,","h":"te","x":"te; Ragozása:<br>sg.2.nom.: σύ (te)<br>sg.2.acc.: σέ v. σε (téged) <br>sg.2.gen.: σοῦ v. σου (tiéd)<br>sg.2.dat.: σοί v. σοι (neked)","i":"12102700200120","s":"Zsolt27,2","m":"sg. 2. acc."},{"g":"ἐν","h":"-ban/-ben","x":"-ban, -ben; között; -val, -vel; által","i":"12102700200130","s":"Zsolt27,2","m":"+ dat."},{"g":"τῷ","h":"a/az","x":"a, az (használata általában mint a magyarban, de eltérés is van); ὁ μέν... ὁ δέ...: az egyik... a másik...; ὁ δέ az pedig, ő pedig <br>m/f/n.sg.nom.: ὁ, ἡ, τό <br>m/f/n.sg.acc.: τόν, τήν, τό <br>m/f/n.sg.gen.: τοῦ, τῆς, τοῦ <br>m/f/n.sg.dat.: τῷ, τῇ, τῷ<br>m/f/n.pl.nom.: οἱ, αἱ, τά <br>m/f/n.pl.acc.: τούς, τάς, τά <br>m/f/n.pl.gen.: τῶν, τῶν, τῶν<br>m/f/n.pl.dat.: τοῖς, ταῖς, τοῖς","i":"12102700200140","s":"Zsolt27,2","m":"n. sg. dat."},{"g":"με","h":"én","x":"én; Ragozása: <br>sg.1.nom.: ἐγώ (én; <abbr class='literature'>ÚSzSz</abbr>: 1473); <br>sg.1.acc.: ἐμέ v. μέ (engem; <abbr class='literature'>ÚSzSz</abbr>: 1691);<br>sg.1.gen.: ἐμού v. μού (enyém; <abbr class='literature'>ÚSzSz</abbr>: 1700); <br>sg.1.dat.: ἐμοί v. μοί (nekem; <abbr class='literature'>ÚSzSz</abbr>: 1698)","i":"12102700200150","s":"Zsolt27,2","m":"sg. 1. acc."},{"g":"αἴρειν","h":"felemelni","x":"1.) felemel, elvesz, (el)visz; 2.) (ruhából) kiszakít; 3.) αἶρε/ἆρον (A.imprt.impf./aor.) kb. \"lógasd föl\", azaz \"feszítsd keresztre\" - Jézust és az Acs-ben Szent Pált","i":"12102700200160","s":"Zsolt27,2","m":"A. inf. impf."},{"g":"χεῖράς","h":"kezeket","x":"kéz; <abbr class='literature'>BÚG</abbr>: ennél az egy szónál történik ilyen rövidülés a pl.dat.-ban.","i":"12102700200170","s":"Zsolt27,2","m":"f. pl. acc."},{"g":"μου","h":"enyém","x":"én; Ragozása: <br>sg.1.nom.: ἐγώ (én; <abbr class='literature'>ÚSzSz</abbr>: 1473); <br>sg.1.acc.: ἐμέ v. μέ (engem; <abbr class='literature'>ÚSzSz</abbr>: 1691);<br>sg.1.gen.: ἐμού v. μού (enyém; <abbr class='literature'>ÚSzSz</abbr>: 1700); <br>sg.1.dat.: ἐμοί v. μοί (nekem; <abbr class='literature'>ÚSzSz</abbr>: 1698)","i":"12102700200180","s":"Zsolt27,2","m":"sg. 1. gen."},{"g":"πρὸς","h":"felé","x":"1. -hoz/-hez/-höz, felé, -ra/-re; 2. (a koinéban a παρά + dat. helyett) -nál/-nél","i":"12102700200190","s":"Zsolt27,2","m":"+ acc."},{"g":"ναὸν","h":"templom","x":"1. templom, 2. a templom legbelsőbb része, szentély 3. szent hely","i":"12102700200200","s":"Zsolt27,2","m":"m. sg. acc."},{"g":"ἅγιόν","h":"szent","x":"szent; A szó értelme: a profántól elkülönített, Isten számára lefoglalt, Isten világához tartozó (a héber <span lang='he'>קָדַשׁ</span> = szent eredeti értelme: elvágni, kultikus értelemben elkülöníteni, elhatárolni attól, ami tisztátalan, közönséges, és Istennek lefoglalni).","i":"12102700200210","s":"Zsolt27,2","m":"m. sg. acc."},{"g":"σου.","h":"tiéd","x":"te; Ragozása:<br>sg.2.nom.: σύ (te)<br>sg.2.acc.: σέ v. σε (téged) <br>sg.2.gen.: σοῦ v. σου (tiéd)<br>sg.2.dat.: σοί v. σοι (neked)","i":"12102700200220","s":"Zsolt27,2","m":"sg. 2. gen."}]},{"w":[{"g":"μὴ συνελκύσῃς μετὰ ἁμαρτωλῶν τὴν ψυχήν μου καὶ μετὰ ἐργαζομένων ἀδικίαν μὴ συναπολέσῃς με τῶν λαλούντων εἰρήνην μετὰ τῶν πλησίον αὐτῶν, κακὰ δὲ ἐν ταῖς καρδίαις αὐτῶν.","h":"ne összevonjad -val/-vel bűnösök a/az lelket enyém és -val/-vel munkálkodók igazságtalanságot nem együtt pusztítsál engem a/az beszélőké békét -val/-vel a/az felebarát/közelálló övék rosszak pedig -ban/-ben a/az szívek övék","x":"ne, nem; talán? ugye nem? A nem indicativusban álló igéket ill. igeneveket tagadja, míg az indicativus tagadására az οὐ, οὐκ, οὐχ használatos (<abbr class='literature'>BÚG</abbr> 22.1.); ου? μή: nagyon nem, semmiképpen nem","i":"12102700300010","s":"Zsolt27,3","m":""},{"g":"μὴ","h":"ne","x":"ne, nem; talán? ugye nem? A nem indicativusban álló igéket ill. igeneveket tagadja, míg az indicativus tagadására az οὐ, οὐκ, οὐχ használatos (<abbr class='literature'>BÚG</abbr> 22.1.); ου? μή: nagyon nem, semmiképpen nem","i":"12102700300010","s":"Zsolt27,3","m":""},{"g":"συνελκύσῃς","h":"összevonjad","x":"összevon, összehúz","i":"12102700300020","s":"Zsolt27,3","m":"A. coni. aor. sg. 2."},{"g":"μετὰ","h":"-val/-vel","x":"1) (+ acc.) után; 2) (+ gen.) -val/-vel","i":"12102700300030","s":"Zsolt27,3","m":"+ gen."},{"g":"ἁμαρτωλῶν","h":"bűnösök","x":"bűnös","i":"12102700300040","s":"Zsolt27,3","m":"m. pl. gen."},{"g":"τὴν","h":"a/az","x":"a, az (használata általában mint a magyarban, de eltérés is van); ὁ μέν... ὁ δέ...: az egyik... a másik...; ὁ δέ az pedig, ő pedig <br>m/f/n.sg.nom.: ὁ, ἡ, τό <br>m/f/n.sg.acc.: τόν, τήν, τό <br>m/f/n.sg.gen.: τοῦ, τῆς, τοῦ <br>m/f/n.sg.dat.: τῷ, τῇ, τῷ<br>m/f/n.pl.nom.: οἱ, αἱ, τά <br>m/f/n.pl.acc.: τούς, τάς, τά <br>m/f/n.pl.gen.: τῶν, τῶν, τῶν<br>m/f/n.pl.dat.: τοῖς, ταῖς, τοῖς","i":"12102700300050","s":"Zsolt27,3","m":"f. sg. acc."},{"g":"ψυχήν","h":"lelket","x":"lehelet, lélek, élet","i":"12102700300060","s":"Zsolt27,3","m":"f. sg. acc."},{"g":"μου","h":"enyém","x":"én; Ragozása: <br>sg.1.nom.: ἐγώ (én; <abbr class='literature'>ÚSzSz</abbr>: 1473); <br>sg.1.acc.: ἐμέ v. μέ (engem; <abbr class='literature'>ÚSzSz</abbr>: 1691);<br>sg.1.gen.: ἐμού v. μού (enyém; <abbr class='literature'>ÚSzSz</abbr>: 1700); <br>sg.1.dat.: ἐμοί v. μοί (nekem; <abbr class='literature'>ÚSzSz</abbr>: 1698)","i":"12102700300070","s":"Zsolt27,3","m":"sg. 1. gen."},{"g":"καὶ","h":"és","x":"és, is","i":"12102700300080","s":"Zsolt27,3","m":""},{"g":"μετὰ","h":"-val/-vel","x":"1) (+ acc.) után; 2) (+ gen.) -val/-vel","i":"12102700300090","s":"Zsolt27,3","m":"+ gen."},{"g":"ἐργαζομένων","h":"munkálkodók","x":"1. működik; munkálkodik; dolgozik; 2. pénzzel kereskedik (vö. <a href='/text/Mt/25/16' class='ref' data-poload='/text/verse-text/Mt/25/16'>Mt 25,16</a>)","i":"12102700300100","s":"Zsolt27,3","m":"D. part. impf. m. pl. gen."},{"g":"ἀδικίαν","h":"igazságtalanságot","x":"jogtalanság, igazságtalanság, gonoszság","i":"12102700300110","s":"Zsolt27,3","m":"f. sg. acc."},{"g":"μὴ","h":"nem","x":"ne, nem; talán? ugye nem? A nem indicativusban álló igéket ill. igeneveket tagadja, míg az indicativus tagadására az οὐ, οὐκ, οὐχ használatos (<abbr class='literature'>BÚG</abbr> 22.1.); ου? μή: nagyon nem, semmiképpen nem","i":"12102700300120","s":"Zsolt27,3","m":""},{"g":"συναπολέσῃς","h":"együtt pusztítsál","x":"1) elpusztul, elveszik együtt; 2) elpusztít együtt","i":"12102700300130","s":"Zsolt27,3","m":"A. coni. aor. sg. 2."},{"g":"με","h":"engem","x":"én; Ragozása: <br>sg.1.nom.: ἐγώ (én; <abbr class='literature'>ÚSzSz</abbr>: 1473); <br>sg.1.acc.: ἐμέ v. μέ (engem; <abbr class='literature'>ÚSzSz</abbr>: 1691);<br>sg.1.gen.: ἐμού v. μού (enyém; <abbr class='literature'>ÚSzSz</abbr>: 1700); <br>sg.1.dat.: ἐμοί v. μοί (nekem; <abbr class='literature'>ÚSzSz</abbr>: 1698)","i":"12102700300140","s":"Zsolt27,3","m":"sg. 1. acc."},{"g":"τῶν","h":"a/az","x":"a, az (használata általában mint a magyarban, de eltérés is van); ὁ μέν... ὁ δέ...: az egyik... a másik...; ὁ δέ az pedig, ő pedig <br>m/f/n.sg.nom.: ὁ, ἡ, τό <br>m/f/n.sg.acc.: τόν, τήν, τό <br>m/f/n.sg.gen.: τοῦ, τῆς, τοῦ <br>m/f/n.sg.dat.: τῷ, τῇ, τῷ<br>m/f/n.pl.nom.: οἱ, αἱ, τά <br>m/f/n.pl.acc.: τούς, τάς, τά <br>m/f/n.pl.gen.: τῶν, τῶν, τῶν<br>m/f/n.pl.dat.: τοῖς, ταῖς, τοῖς","i":"12102700300150","s":"Zsolt27,3","m":"m. pl. gen."},{"g":"λαλούντων","h":"beszélőké","x":"szól, beszél","i":"12102700300160","s":"Zsolt27,3","m":"A. part. impf. m. pl. gen."},{"g":"εἰρήνην","h":"békét","x":"béke, békesség","i":"12102700300170","s":"Zsolt27,3","m":"f. sg. acc."},{"g":"μετὰ","h":"-val/-vel","x":"1) (+ acc.) után; 2) (+ gen.) -val/-vel","i":"12102700300180","s":"Zsolt27,3","m":"+ gen."},{"g":"τῶν","h":"a/az","x":"a, az (használata általában mint a magyarban, de eltérés is van); ὁ μέν... ὁ δέ...: az egyik... a másik...; ὁ δέ az pedig, ő pedig <br>m/f/n.sg.nom.: ὁ, ἡ, τό <br>m/f/n.sg.acc.: τόν, τήν, τό <br>m/f/n.sg.gen.: τοῦ, τῆς, τοῦ <br>m/f/n.sg.dat.: τῷ, τῇ, τῷ<br>m/f/n.pl.nom.: οἱ, αἱ, τά <br>m/f/n.pl.acc.: τούς, τάς, τά <br>m/f/n.pl.gen.: τῶν, τῶν, τῶν<br>m/f/n.pl.dat.: τοῖς, ταῖς, τοῖς","i":"12102700300190","s":"Zsolt27,3","m":"m. pl. gen."},{"g":"πλησίον","h":"felebarát/közelálló","x":"1. közel; (Így csak <a href='/text/Jn/4/5' class='ref' data-poload='/text/verse-text/Jn/4/5'>Jn 4,5</a>: πλησίον τοῦ χωρίου - a vidék közelében) 2. (nm.indecl.) ὁ πλησίον: felebarát, közelálló (vö: Ef 4,25: τοῦ πλησίον; Róm 13,10: τῷ πλησίον)","i":"12102700300200","s":"Zsolt27,3","m":""},{"g":"αὐτῶν,","h":"övék","x":"1) (pron.pers.) ő, ők (m/f/n.sg/pl.3. - neutrumban, pl. ha gyermekről van szó) 2) (pron.dem.) az, azok (n.sg/pl.3.) 3) (pron.refl.) téged magadat, temagadé, neked magadnak, őt magát, övé magáé, neki magának stb. (m/f.sg/pl.2/3.) vö: εἁυτοῦ, -ῆς, -οῦ (1438); 4) ὁ αὐτός: ugyanaz (pron.dem.)","i":"12102700300210","s":"Zsolt27,3","m":"m. pl. 3. gen."},{"g":"κακὰ","h":"rosszak","x":"rossz","i":"12102700300220","s":"Zsolt27,3","m":"n. pl. nom."},{"g":"δὲ","h":"pedig","x":"pedig; μέν... δέ...: egyrészt..., másrészt\u2026; újabb δέ...: harmadrészt v. továbbá","i":"12102700300230","s":"Zsolt27,3","m":""},{"g":"ἐν","h":"-ban/-ben","x":"-ban, -ben; között; -val, -vel; által","i":"12102700300240","s":"Zsolt27,3","m":"+ dat."},{"g":"ταῖς","h":"a/az","x":"a, az (használata általában mint a magyarban, de eltérés is van); ὁ μέν... ὁ δέ...: az egyik... a másik...; ὁ δέ az pedig, ő pedig <br>m/f/n.sg.nom.: ὁ, ἡ, τό <br>m/f/n.sg.acc.: τόν, τήν, τό <br>m/f/n.sg.gen.: τοῦ, τῆς, τοῦ <br>m/f/n.sg.dat.: τῷ, τῇ, τῷ<br>m/f/n.pl.nom.: οἱ, αἱ, τά <br>m/f/n.pl.acc.: τούς, τάς, τά <br>m/f/n.pl.gen.: τῶν, τῶν, τῶν<br>m/f/n.pl.dat.: τοῖς, ταῖς, τοῖς","i":"12102700300250","s":"Zsolt27,3","m":"f. pl. dat."},{"g":"καρδίαις","h":"szívek","x":"szív","i":"12102700300260","s":"Zsolt27,3","m":"f. pl. dat."},{"g":"αὐτῶν.","h":"övék","x":"1) (pron.pers.) ő, ők (m/f/n.sg/pl.3. - neutrumban, pl. ha gyermekről van szó) 2) (pron.dem.) az, azok (n.sg/pl.3.) 3) (pron.refl.) téged magadat, temagadé, neked magadnak, őt magát, övé magáé, neki magának stb. (m/f.sg/pl.2/3.) vö: εἁυτοῦ, -ῆς, -οῦ (1438); 4) ὁ αὐτός: ugyanaz (pron.dem.)","i":"12102700300270","s":"Zsolt27,3","m":"m. pl. 3. gen."}]},{"w":[{"g":"δὸς αὐτοῖς κατὰ τὰ ἔργα αὐτῶν καὶ κατὰ τὴν πονηρίαν τῶν ἐπιτηδευμάτων αὐτῶν· κατὰ τὰ ἔργα τῶν χειρῶν αὐτῶν δὸς αὐτοῖς, ἀπόδος τὸ ἀνταπόδομα αὐτῶν αὐτοῖς.","h":"add nekik szerint a/az tettek övék és szerint a/az gonoszság a/az törekvéseké övék szerint a/az tettek a/az kezeké övék adj nekik add meg a/az megtorlást övék nekik","x":"1. ajándékoz; 2. átad; 3. feleségül ad; 4. felajánl (istennek); 5. szerez, biztosít vkinek vmit; 6. kiszolgáltat; 7. átad, hagyományoz; 8. szolgáltat, ad; 9. megenged; 10. elenged, megbocsát; 11. elrendel, megparancsol; 12. átadja magát vminek","i":"12102700400010","s":"Zsolt27,4","m":"A. imprt. aor. sg. 2."},{"g":"δὸς","h":"add","x":"1. ajándékoz; 2. átad; 3. feleségül ad; 4. felajánl (istennek); 5. szerez, biztosít vkinek vmit; 6. kiszolgáltat; 7. átad, hagyományoz; 8. szolgáltat, ad; 9. megenged; 10. elenged, megbocsát; 11. elrendel, megparancsol; 12. átadja magát vminek","i":"12102700400010","s":"Zsolt27,4","m":"A. imprt. aor. sg. 2."},{"g":"αὐτοῖς","h":"nekik","x":"1) (pron.pers.) ő, ők (m/f/n.sg/pl.3. - neutrumban, pl. ha gyermekről van szó) 2) (pron.dem.) az, azok (n.sg/pl.3.) 3) (pron.refl.) téged magadat, temagadé, neked magadnak, őt magát, övé magáé, neki magának stb. (m/f.sg/pl.2/3.) vö: εἁυτοῦ, -ῆς, -οῦ (1438); 4) ὁ αὐτός: ugyanaz (pron.dem.)","i":"12102700400020","s":"Zsolt27,4","m":"m. pl. 3. dat."},{"g":"κατὰ","h":"szerint","x":"1) (+ acc.) szerint; szerte; előtt; között; 2) (+ gen.) ellen, szemben","i":"12102700400030","s":"Zsolt27,4","m":"+ acc."},{"g":"τὰ","h":"a/az","x":"a, az (használata általában mint a magyarban, de eltérés is van); ὁ μέν... ὁ δέ...: az egyik... a másik...; ὁ δέ az pedig, ő pedig <br>m/f/n.sg.nom.: ὁ, ἡ, τό <br>m/f/n.sg.acc.: τόν, τήν, τό <br>m/f/n.sg.gen.: τοῦ, τῆς, τοῦ <br>m/f/n.sg.dat.: τῷ, τῇ, τῷ<br>m/f/n.pl.nom.: οἱ, αἱ, τά <br>m/f/n.pl.acc.: τούς, τάς, τά <br>m/f/n.pl.gen.: τῶν, τῶν, τῶν<br>m/f/n.pl.dat.: τοῖς, ταῖς, τοῖς","i":"12102700400040","s":"Zsolt27,4","m":"n. pl. acc."},{"g":"ἔργα","h":"tettek","x":"munka, tett, cselekedet","i":"12102700400050","s":"Zsolt27,4","m":"n. pl. acc."},{"g":"αὐτῶν","h":"övék","x":"1) (pron.pers.) ő, ők (m/f/n.sg/pl.3. - neutrumban, pl. ha gyermekről van szó) 2) (pron.dem.) az, azok (n.sg/pl.3.) 3) (pron.refl.) téged magadat, temagadé, neked magadnak, őt magát, övé magáé, neki magának stb. (m/f.sg/pl.2/3.) vö: εἁυτοῦ, -ῆς, -οῦ (1438); 4) ὁ αὐτός: ugyanaz (pron.dem.)","i":"12102700400060","s":"Zsolt27,4","m":"m. pl. 3. gen."},{"g":"καὶ","h":"és","x":"és, is","i":"12102700400070","s":"Zsolt27,4","m":""},{"g":"κατὰ","h":"szerint","x":"1) (+ acc.) szerint; szerte; előtt; között; 2) (+ gen.) ellen, szemben","i":"12102700400080","s":"Zsolt27,4","m":"+ acc."},{"g":"τὴν","h":"a/az","x":"a, az (használata általában mint a magyarban, de eltérés is van); ὁ μέν... ὁ δέ...: az egyik... a másik...; ὁ δέ az pedig, ő pedig <br>m/f/n.sg.nom.: ὁ, ἡ, τό <br>m/f/n.sg.acc.: τόν, τήν, τό <br>m/f/n.sg.gen.: τοῦ, τῆς, τοῦ <br>m/f/n.sg.dat.: τῷ, τῇ, τῷ<br>m/f/n.pl.nom.: οἱ, αἱ, τά <br>m/f/n.pl.acc.: τούς, τάς, τά <br>m/f/n.pl.gen.: τῶν, τῶν, τῶν<br>m/f/n.pl.dat.: τοῖς, ταῖς, τοῖς","i":"12102700400090","s":"Zsolt27,4","m":"f. sg. acc."},{"g":"πονηρίαν","h":"gonoszság","x":"gonoszság","i":"12102700400100","s":"Zsolt27,4","m":"f. sg. acc."},{"g":"τῶν","h":"a/az","x":"a, az (használata általában mint a magyarban, de eltérés is van); ὁ μέν... ὁ δέ...: az egyik... a másik...; ὁ δέ az pedig, ő pedig <br>m/f/n.sg.nom.: ὁ, ἡ, τό <br>m/f/n.sg.acc.: τόν, τήν, τό <br>m/f/n.sg.gen.: τοῦ, τῆς, τοῦ <br>m/f/n.sg.dat.: τῷ, τῇ, τῷ<br>m/f/n.pl.nom.: οἱ, αἱ, τά <br>m/f/n.pl.acc.: τούς, τάς, τά <br>m/f/n.pl.gen.: τῶν, τῶν, τῶν<br>m/f/n.pl.dat.: τοῖς, ταῖς, τοῖς","i":"12102700400110","s":"Zsolt27,4","m":"n. pl. gen."},{"g":"ἐπιτηδευμάτων","h":"törekvéseké","x":"törekvés, ügy, gyakorlat, szokás, üzelmek","i":"12102700400120","s":"Zsolt27,4","m":"n. pl. gen."},{"g":"αὐτῶν·","h":"övék","x":"1) (pron.pers.) ő, ők (m/f/n.sg/pl.3. - neutrumban, pl. ha gyermekről van szó) 2) (pron.dem.) az, azok (n.sg/pl.3.) 3) (pron.refl.) téged magadat, temagadé, neked magadnak, őt magát, övé magáé, neki magának stb. (m/f.sg/pl.2/3.) vö: εἁυτοῦ, -ῆς, -οῦ (1438); 4) ὁ αὐτός: ugyanaz (pron.dem.)","i":"12102700400130","s":"Zsolt27,4","m":"m. pl. 3. gen."},{"g":"κατὰ","h":"szerint","x":"1) (+ acc.) szerint; szerte; előtt; között; 2) (+ gen.) ellen, szemben","i":"12102700400140","s":"Zsolt27,4","m":"+ acc."},{"g":"τὰ","h":"a/az","x":"a, az (használata általában mint a magyarban, de eltérés is van); ὁ μέν... ὁ δέ...: az egyik... a másik...; ὁ δέ az pedig, ő pedig <br>m/f/n.sg.nom.: ὁ, ἡ, τό <br>m/f/n.sg.acc.: τόν, τήν, τό <br>m/f/n.sg.gen.: τοῦ, τῆς, τοῦ <br>m/f/n.sg.dat.: τῷ, τῇ, τῷ<br>m/f/n.pl.nom.: οἱ, αἱ, τά <br>m/f/n.pl.acc.: τούς, τάς, τά <br>m/f/n.pl.gen.: τῶν, τῶν, τῶν<br>m/f/n.pl.dat.: τοῖς, ταῖς, τοῖς","i":"12102700400150","s":"Zsolt27,4","m":"n. pl. acc."},{"g":"ἔργα","h":"tettek","x":"munka, tett, cselekedet","i":"12102700400160","s":"Zsolt27,4","m":"n. pl. acc."},{"g":"τῶν","h":"a/az","x":"a, az (használata általában mint a magyarban, de eltérés is van); ὁ μέν... ὁ δέ...: az egyik... a másik...; ὁ δέ az pedig, ő pedig <br>m/f/n.sg.nom.: ὁ, ἡ, τό <br>m/f/n.sg.acc.: τόν, τήν, τό <br>m/f/n.sg.gen.: τοῦ, τῆς, τοῦ <br>m/f/n.sg.dat.: τῷ, τῇ, τῷ<br>m/f/n.pl.nom.: οἱ, αἱ, τά <br>m/f/n.pl.acc.: τούς, τάς, τά <br>m/f/n.pl.gen.: τῶν, τῶν, τῶν<br>m/f/n.pl.dat.: τοῖς, ταῖς, τοῖς","i":"12102700400170","s":"Zsolt27,4","m":"f. pl. gen."},{"g":"χειρῶν","h":"kezeké","x":"kéz; <abbr class='literature'>BÚG</abbr>: ennél az egy szónál történik ilyen rövidülés a pl.dat.-ban.","i":"12102700400180","s":"Zsolt27,4","m":"f. pl. gen."},{"g":"αὐτῶν","h":"övék","x":"1) (pron.pers.) ő, ők (m/f/n.sg/pl.3. - neutrumban, pl. ha gyermekről van szó) 2) (pron.dem.) az, azok (n.sg/pl.3.) 3) (pron.refl.) téged magadat, temagadé, neked magadnak, őt magát, övé magáé, neki magának stb. (m/f.sg/pl.2/3.) vö: εἁυτοῦ, -ῆς, -οῦ (1438); 4) ὁ αὐτός: ugyanaz (pron.dem.)","i":"12102700400190","s":"Zsolt27,4","m":"m. pl. 3. gen."},{"g":"δὸς","h":"adj","x":"1. ajándékoz; 2. átad; 3. feleségül ad; 4. felajánl (istennek); 5. szerez, biztosít vkinek vmit; 6. kiszolgáltat; 7. átad, hagyományoz; 8. szolgáltat, ad; 9. megenged; 10. elenged, megbocsát; 11. elrendel, megparancsol; 12. átadja magát vminek","i":"12102700400200","s":"Zsolt27,4","m":"A. imprt. aor. sg. 2."},{"g":"αὐτοῖς,","h":"nekik","x":"1) (pron.pers.) ő, ők (m/f/n.sg/pl.3. - neutrumban, pl. ha gyermekről van szó) 2) (pron.dem.) az, azok (n.sg/pl.3.) 3) (pron.refl.) téged magadat, temagadé, neked magadnak, őt magát, övé magáé, neki magának stb. (m/f.sg/pl.2/3.) vö: εἁυτοῦ, -ῆς, -οῦ (1438); 4) ὁ αὐτός: ugyanaz (pron.dem.)","i":"12102700400210","s":"Zsolt27,4","m":"m. pl. 3. dat."},{"g":"ἀπόδος","h":"add meg","x":"(tartozást) megad, (számot) ad megbízásáról, fizet","i":"12102700400220","s":"Zsolt27,4","m":"A. imprt. aor. sg. 2."},{"g":"τὸ","h":"a/az","x":"a, az (használata általában mint a magyarban, de eltérés is van); ὁ μέν... ὁ δέ...: az egyik... a másik...; ὁ δέ az pedig, ő pedig <br>m/f/n.sg.nom.: ὁ, ἡ, τό <br>m/f/n.sg.acc.: τόν, τήν, τό <br>m/f/n.sg.gen.: τοῦ, τῆς, τοῦ <br>m/f/n.sg.dat.: τῷ, τῇ, τῷ<br>m/f/n.pl.nom.: οἱ, αἱ, τά <br>m/f/n.pl.acc.: τούς, τάς, τά <br>m/f/n.pl.gen.: τῶν, τῶν, τῶν<br>m/f/n.pl.dat.: τοῖς, ταῖς, τοῖς","i":"12102700400230","s":"Zsolt27,4","m":"n. sg. acc."},{"g":"ἀνταπόδομα","h":"megtorlást","x":"1) viszonzás (jótetté); 2) megtorlás (gonosztetté)","i":"12102700400240","s":"Zsolt27,4","m":"n. sg. acc."},{"g":"αὐτῶν","h":"övék","x":"1) (pron.pers.) ő, ők (m/f/n.sg/pl.3. - neutrumban, pl. ha gyermekről van szó) 2) (pron.dem.) az, azok (n.sg/pl.3.) 3) (pron.refl.) téged magadat, temagadé, neked magadnak, őt magát, övé magáé, neki magának stb. (m/f.sg/pl.2/3.) vö: εἁυτοῦ, -ῆς, -οῦ (1438); 4) ὁ αὐτός: ugyanaz (pron.dem.)","i":"12102700400250","s":"Zsolt27,4","m":"m. pl. 3. gen."},{"g":"αὐτοῖς.","h":"nekik","x":"1) (pron.pers.) ő, ők (m/f/n.sg/pl.3. - neutrumban, pl. ha gyermekről van szó) 2) (pron.dem.) az, azok (n.sg/pl.3.) 3) (pron.refl.) téged magadat, temagadé, neked magadnak, őt magát, övé magáé, neki magának stb. (m/f.sg/pl.2/3.) vö: εἁυτοῦ, -ῆς, -οῦ (1438); 4) ὁ αὐτός: ugyanaz (pron.dem.)","i":"12102700400260","s":"Zsolt27,4","m":"m. pl. 3. dat."}]},{"w":[{"g":"ὅτι οὐ συνῆκαν εἰς τὰ ἔργα κυρίου καὶ εἰς τὰ ἔργα τῶν χειρῶν αὐτοῦ· καθελεῖς αὐτοὺς καὶ οὐ μὴ οἰκοδομήσεις αὐτούς.","h":"mert nem fogták föl -ra/-re a/az tettek Úré és -ra/-re a/az tettek a/az kezeké övé ledöntöd majd őket és nem nem felépíted majd őket","x":"1. hogy; 2. mert","i":"12102700500010","s":"Zsolt27,5","m":""},{"g":"ὅτι","h":"mert","x":"1. hogy; 2. mert","i":"12102700500010","s":"Zsolt27,5","m":""},{"g":"οὐ","h":"nem","x":"nem; 1) (hangsúlytalanul, mássalhangzó előtt: οὐ; magánhangzó előtt: οὐκ; hehezetes szó előtt: οὐχ) általában az indicativus tagadása, a többi igemódot és az igenemeket a μή tagadja (<abbr class='literature'>BÚG</abbr> 22.1.); 2) (hangsúlyosan: οὔ) hangsúlyos nem \"igen vagy nem\" jellegű kérdésekben, vagy egész mondatok, gondolatmenetek tagadásában; 3) οὐ μή: nagyon nem, semmiképpen nem","i":"12102700500020","s":"Zsolt27,5","m":""},{"g":"συνῆκαν","h":"fogták föl","x":"1) felfog, belát, okul; 2) együtt ül, ülésezik","i":"12102700500030","s":"Zsolt27,5","m":"A. ind. aor. pl. 3."},{"g":"εἰς","h":"-ra/-re","x":"-ba/-be, -ra/-re, ellen","i":"12102700500040","s":"Zsolt27,5","m":"+ acc."},{"g":"τὰ","h":"a/az","x":"a, az (használata általában mint a magyarban, de eltérés is van); ὁ μέν... ὁ δέ...: az egyik... a másik...; ὁ δέ az pedig, ő pedig <br>m/f/n.sg.nom.: ὁ, ἡ, τό <br>m/f/n.sg.acc.: τόν, τήν, τό <br>m/f/n.sg.gen.: τοῦ, τῆς, τοῦ <br>m/f/n.sg.dat.: τῷ, τῇ, τῷ<br>m/f/n.pl.nom.: οἱ, αἱ, τά <br>m/f/n.pl.acc.: τούς, τάς, τά <br>m/f/n.pl.gen.: τῶν, τῶν, τῶν<br>m/f/n.pl.dat.: τοῖς, ταῖς, τοῖς","i":"12102700500050","s":"Zsolt27,5","m":"n. pl. acc."},{"g":"ἔργα","h":"tettek","x":"munka, tett, cselekedet","i":"12102700500060","s":"Zsolt27,5","m":"n. pl. acc."},{"g":"κυρίου","h":"Úré","x":"úr; Úr - A Septuagintában legtöbbször a négybetűs Istennév, a Tetragrammaton <span lang='he'>יהוה</span> helyettesítője","i":"12102700500070","s":"Zsolt27,5","m":"m. sg. gen."},{"g":"καὶ","h":"és","x":"és, is","i":"12102700500080","s":"Zsolt27,5","m":""},{"g":"εἰς","h":"-ra/-re","x":"-ba/-be, -ra/-re, ellen","i":"12102700500090","s":"Zsolt27,5","m":"+ acc."},{"g":"τὰ","h":"a/az","x":"a, az (használata általában mint a magyarban, de eltérés is van); ὁ μέν... ὁ δέ...: az egyik... a másik...; ὁ δέ az pedig, ő pedig <br>m/f/n.sg.nom.: ὁ, ἡ, τό <br>m/f/n.sg.acc.: τόν, τήν, τό <br>m/f/n.sg.gen.: τοῦ, τῆς, τοῦ <br>m/f/n.sg.dat.: τῷ, τῇ, τῷ<br>m/f/n.pl.nom.: οἱ, αἱ, τά <br>m/f/n.pl.acc.: τούς, τάς, τά <br>m/f/n.pl.gen.: τῶν, τῶν, τῶν<br>m/f/n.pl.dat.: τοῖς, ταῖς, τοῖς","i":"12102700500100","s":"Zsolt27,5","m":"n. pl. acc."},{"g":"ἔργα","h":"tettek","x":"munka, tett, cselekedet","i":"12102700500110","s":"Zsolt27,5","m":"n. pl. acc."},{"g":"τῶν","h":"a/az","x":"a, az (használata általában mint a magyarban, de eltérés is van); ὁ μέν... ὁ δέ...: az egyik... a másik...; ὁ δέ az pedig, ő pedig <br>m/f/n.sg.nom.: ὁ, ἡ, τό <br>m/f/n.sg.acc.: τόν, τήν, τό <br>m/f/n.sg.gen.: τοῦ, τῆς, τοῦ <br>m/f/n.sg.dat.: τῷ, τῇ, τῷ<br>m/f/n.pl.nom.: οἱ, αἱ, τά <br>m/f/n.pl.acc.: τούς, τάς, τά <br>m/f/n.pl.gen.: τῶν, τῶν, τῶν<br>m/f/n.pl.dat.: τοῖς, ταῖς, τοῖς","i":"12102700500120","s":"Zsolt27,5","m":"f. pl. gen."},{"g":"χειρῶν","h":"kezeké","x":"kéz; <abbr class='literature'>BÚG</abbr>: ennél az egy szónál történik ilyen rövidülés a pl.dat.-ban.","i":"12102700500130","s":"Zsolt27,5","m":"f. pl. gen."},{"g":"αὐτοῦ·","h":"övé","x":"1) (pron.pers.) ő, ők (m/f/n.sg/pl.3. - neutrumban, pl. ha gyermekről van szó) 2) (pron.dem.) az, azok (n.sg/pl.3.) 3) (pron.refl.) téged magadat, temagadé, neked magadnak, őt magát, övé magáé, neki magának stb. (m/f.sg/pl.2/3.) vö: εἁυτοῦ, -ῆς, -οῦ (1438); 4) ὁ αὐτός: ugyanaz (pron.dem.)","i":"12102700500140","s":"Zsolt27,5","m":"m. sg. 3. gen."},{"g":"καθελεῖς","h":"ledöntöd majd","x":"levesz, letaszít, ledönt","i":"12102700500150","s":"Zsolt27,5","m":"A. fut. sg. 2."},{"g":"αὐτοὺς","h":"őket","x":"1) (pron.pers.) ő, ők (m/f/n.sg/pl.3. - neutrumban, pl. ha gyermekről van szó) 2) (pron.dem.) az, azok (n.sg/pl.3.) 3) (pron.refl.) téged magadat, temagadé, neked magadnak, őt magát, övé magáé, neki magának stb. (m/f.sg/pl.2/3.) vö: εἁυτοῦ, -ῆς, -οῦ (1438); 4) ὁ αὐτός: ugyanaz (pron.dem.)","i":"12102700500160","s":"Zsolt27,5","m":"m. pl. 3. acc."},{"g":"καὶ","h":"és","x":"és, is","i":"12102700500170","s":"Zsolt27,5","m":""},{"g":"οὐ","h":"nem","x":"nem; 1) (hangsúlytalanul, mássalhangzó előtt: οὐ; magánhangzó előtt: οὐκ; hehezetes szó előtt: οὐχ) általában az indicativus tagadása, a többi igemódot és az igenemeket a μή tagadja (<abbr class='literature'>BÚG</abbr> 22.1.); 2) (hangsúlyosan: οὔ) hangsúlyos nem \"igen vagy nem\" jellegű kérdésekben, vagy egész mondatok, gondolatmenetek tagadásában; 3) οὐ μή: nagyon nem, semmiképpen nem","i":"12102700500180","s":"Zsolt27,5","m":""},{"g":"μὴ","h":"nem","x":"ne, nem; talán? ugye nem? A nem indicativusban álló igéket ill. igeneveket tagadja, míg az indicativus tagadására az οὐ, οὐκ, οὐχ használatos (<abbr class='literature'>BÚG</abbr> 22.1.); ου? μή: nagyon nem, semmiképpen nem","i":"12102700500190","s":"Zsolt27,5","m":""},{"g":"οἰκοδομήσεις","h":"felépíted majd","x":"épít, fölépít","i":"12102700500200","s":"Zsolt27,5","m":"A. fut. sg. 2."},{"g":"αὐτούς.","h":"őket","x":"1) (pron.pers.) ő, ők (m/f/n.sg/pl.3. - neutrumban, pl. ha gyermekről van szó) 2) (pron.dem.) az, azok (n.sg/pl.3.) 3) (pron.refl.) téged magadat, temagadé, neked magadnak, őt magát, övé magáé, neki magának stb. (m/f.sg/pl.2/3.) vö: εἁυτοῦ, -ῆς, -οῦ (1438); 4) ὁ αὐτός: ugyanaz (pron.dem.)","i":"12102700500210","s":"Zsolt27,5","m":"m. pl. 3. acc."}]},{"w":[{"g":"εὐλογητὸς κύριος, ὅτι εἰσήκουσεν τῆς φωνῆς τῆς δεήσεώς μου.","h":"áldott Úr hogy meghallgatta a/az hangot a/az könyörgésé enyém","x":"áldott","i":"12102700600010","s":"Zsolt27,6","m":"m. sg. nom."},{"g":"εὐλογητὸς","h":"áldott","x":"áldott","i":"12102700600010","s":"Zsolt27,6","m":"m. sg. nom."},{"g":"κύριος,","h":"Úr","x":"úr; Úr - A Septuagintában legtöbbször a négybetűs Istennév, a Tetragrammaton <span lang='he'>יהוה</span> helyettesítője","i":"12102700600020","s":"Zsolt27,6","m":"m. sg. nom."},{"g":"ὅτι","h":"hogy","x":"1. hogy; 2. mert","i":"12102700600030","s":"Zsolt27,6","m":""},{"g":"εἰσήκουσεν","h":"meghallgatta","x":"1) (A) odafigyel, ráhallgat; 2) meghallgat, megért vmit; 3) (P) meghallgatásra talál","i":"12102700600040","s":"Zsolt27,6","m":"A. ind. aor. sg. 3."},{"g":"τῆς","h":"a/az","x":"a, az (használata általában mint a magyarban, de eltérés is van); ὁ μέν... ὁ δέ...: az egyik... a másik...; ὁ δέ az pedig, ő pedig <br>m/f/n.sg.nom.: ὁ, ἡ, τό <br>m/f/n.sg.acc.: τόν, τήν, τό <br>m/f/n.sg.gen.: τοῦ, τῆς, τοῦ <br>m/f/n.sg.dat.: τῷ, τῇ, τῷ<br>m/f/n.pl.nom.: οἱ, αἱ, τά <br>m/f/n.pl.acc.: τούς, τάς, τά <br>m/f/n.pl.gen.: τῶν, τῶν, τῶν<br>m/f/n.pl.dat.: τοῖς, ταῖς, τοῖς","i":"12102700600050","s":"Zsolt27,6","m":"f. sg. gen."},{"g":"φωνῆς","h":"hangot","x":"hang","i":"12102700600060","s":"Zsolt27,6","m":"f. sg. gen."},{"g":"τῆς","h":"a/az","x":"a, az (használata általában mint a magyarban, de eltérés is van); ὁ μέν... ὁ δέ...: az egyik... a másik...; ὁ δέ az pedig, ő pedig <br>m/f/n.sg.nom.: ὁ, ἡ, τό <br>m/f/n.sg.acc.: τόν, τήν, τό <br>m/f/n.sg.gen.: τοῦ, τῆς, τοῦ <br>m/f/n.sg.dat.: τῷ, τῇ, τῷ<br>m/f/n.pl.nom.: οἱ, αἱ, τά <br>m/f/n.pl.acc.: τούς, τάς, τά <br>m/f/n.pl.gen.: τῶν, τῶν, τῶν<br>m/f/n.pl.dat.: τοῖς, ταῖς, τοῖς","i":"12102700600070","s":"Zsolt27,6","m":"f. sg. gen."},{"g":"δεήσεώς","h":"könyörgésé","x":"könyörgés","i":"12102700600080","s":"Zsolt27,6","m":"f. sg. gen."},{"g":"μου.","h":"enyém","x":"én; Ragozása: <br>sg.1.nom.: ἐγώ (én; <abbr class='literature'>ÚSzSz</abbr>: 1473); <br>sg.1.acc.: ἐμέ v. μέ (engem; <abbr class='literature'>ÚSzSz</abbr>: 1691);<br>sg.1.gen.: ἐμού v. μού (enyém; <abbr class='literature'>ÚSzSz</abbr>: 1700); <br>sg.1.dat.: ἐμοί v. μοί (nekem; <abbr class='literature'>ÚSzSz</abbr>: 1698)","i":"12102700600090","s":"Zsolt27,6","m":"sg. 1. gen."}]},{"w":[{"g":"κύριος βοηθός μου καὶ ὑπερασπιστής μου· ἐπ᾽ αὐτῷ ἤλπισεν ἡ καρδία μου, καὶ ἐβοηθήθην, καὶ ἀνέθαλεν ἡ σάρξ μου· καὶ ἐκ θελήματός μου ἐξομολογήσομαι αὐτῷ.","h":"Úr segítő enyém és támogató enyém -ban/-ben ő remélt a/az szív enyém és megsegíttettem és kisarjadt a/az hústest enyém és -tól/-től öröm enyém vallomást teszek majd neki","x":"úr; Úr - A Septuagintában legtöbbször a négybetűs Istennév, a Tetragrammaton <span lang='he'>יהוה</span> helyettesítője","i":"12102700700010","s":"Zsolt27,7","m":"m. sg. nom."},{"g":"κύριος","h":"Úr","x":"úr; Úr - A Septuagintában legtöbbször a négybetűs Istennév, a Tetragrammaton <span lang='he'>יהוה</span> helyettesítője","i":"12102700700010","s":"Zsolt27,7","m":"m. sg. nom."},{"g":"βοηθός","h":"segítő","x":"segítő","i":"12102700700020","s":"Zsolt27,7","m":"m. sg. nom."},{"g":"μου","h":"enyém","x":"én; Ragozása: <br>sg.1.nom.: ἐγώ (én; <abbr class='literature'>ÚSzSz</abbr>: 1473); <br>sg.1.acc.: ἐμέ v. μέ (engem; <abbr class='literature'>ÚSzSz</abbr>: 1691);<br>sg.1.gen.: ἐμού v. μού (enyém; <abbr class='literature'>ÚSzSz</abbr>: 1700); <br>sg.1.dat.: ἐμοί v. μοί (nekem; <abbr class='literature'>ÚSzSz</abbr>: 1698)","i":"12102700700030","s":"Zsolt27,7","m":"sg. 1. gen."},{"g":"καὶ","h":"és","x":"és, is","i":"12102700700040","s":"Zsolt27,7","m":""},{"g":"ὑπερασπιστής","h":"támogató","x":"védelmező, támogató","i":"12102700700050","s":"Zsolt27,7","m":"m. sg. nom."},{"g":"μου·","h":"enyém","x":"én; Ragozása: <br>sg.1.nom.: ἐγώ (én; <abbr class='literature'>ÚSzSz</abbr>: 1473); <br>sg.1.acc.: ἐμέ v. μέ (engem; <abbr class='literature'>ÚSzSz</abbr>: 1691);<br>sg.1.gen.: ἐμού v. μού (enyém; <abbr class='literature'>ÚSzSz</abbr>: 1700); <br>sg.1.dat.: ἐμοί v. μοί (nekem; <abbr class='literature'>ÚSzSz</abbr>: 1698)","i":"12102700700060","s":"Zsolt27,7","m":"sg. 1. gen."},{"g":"ἐπ᾽","h":"-ban/-ben","x":"1) (+ acc.) -ra/-re; 1a) ἐπὶ τὸ αὐτὸ: együtt (<abbr class='literature'>ÚGMSz</abbr>: A lukácsi nyelvhasználatra jellemző kifejezés, vö. <a href='/text/Lk/17/35' class='ref' data-poload='/text/verse-text/Lk/17/35'>Lk 17,35</a>; Acs 1,15; 2,1; 2,44); 2) (+ gen.) -on/-en/-ön; 3) (+ dat.) -on/-en/-ön, -ban/-ben; A koinéban már gyakran keveredik az esetek használata.","i":"12102700700070","s":"Zsolt27,7","m":"+ dat."},{"g":"αὐτῷ","h":"ő","x":"1) (pron.pers.) ő, ők (m/f/n.sg/pl.3. - neutrumban, pl. ha gyermekről van szó) 2) (pron.dem.) az, azok (n.sg/pl.3.) 3) (pron.refl.) téged magadat, temagadé, neked magadnak, őt magát, övé magáé, neki magának stb. (m/f.sg/pl.2/3.) vö: εἁυτοῦ, -ῆς, -οῦ (1438); 4) ὁ αὐτός: ugyanaz (pron.dem.)","i":"12102700700080","s":"Zsolt27,7","m":"m. sg. 3. dat."},{"g":"ἤλπισεν","h":"remélt","x":"remél, vár","i":"12102700700090","s":"Zsolt27,7","m":"A. ind. aor. sg. 3."},{"g":"ἡ","h":"a/az","x":"a, az (használata általában mint a magyarban, de eltérés is van); ὁ μέν... ὁ δέ...: az egyik... a másik...; ὁ δέ az pedig, ő pedig <br>m/f/n.sg.nom.: ὁ, ἡ, τό <br>m/f/n.sg.acc.: τόν, τήν, τό <br>m/f/n.sg.gen.: τοῦ, τῆς, τοῦ <br>m/f/n.sg.dat.: τῷ, τῇ, τῷ<br>m/f/n.pl.nom.: οἱ, αἱ, τά <br>m/f/n.pl.acc.: τούς, τάς, τά <br>m/f/n.pl.gen.: τῶν, τῶν, τῶν<br>m/f/n.pl.dat.: τοῖς, ταῖς, τοῖς","i":"12102700700100","s":"Zsolt27,7","m":"f. sg. nom."},{"g":"καρδία","h":"szív","x":"szív","i":"12102700700110","s":"Zsolt27,7","m":"f. sg. nom."},{"g":"μου,","h":"enyém","x":"én; Ragozása: <br>sg.1.nom.: ἐγώ (én; <abbr class='literature'>ÚSzSz</abbr>: 1473); <br>sg.1.acc.: ἐμέ v. μέ (engem; <abbr class='literature'>ÚSzSz</abbr>: 1691);<br>sg.1.gen.: ἐμού v. μού (enyém; <abbr class='literature'>ÚSzSz</abbr>: 1700); <br>sg.1.dat.: ἐμοί v. μοί (nekem; <abbr class='literature'>ÚSzSz</abbr>: 1698)","i":"12102700700120","s":"Zsolt27,7","m":"sg. 1. gen."},{"g":"καὶ","h":"és","x":"és, is","i":"12102700700130","s":"Zsolt27,7","m":""},{"g":"ἐβοηθήθην,","h":"megsegíttettem","x":"segít, segítséget nyújt","i":"12102700700140","s":"Zsolt27,7","m":"P. ind. aor. sg. 1."},{"g":"καὶ","h":"és","x":"és, is","i":"12102700700150","s":"Zsolt27,7","m":""},{"g":"ἀνέθαλεν","h":"kisarjadt","x":"1. (A) (ki)sarjaszt; 2. (M) felvirágzik, kisarjad","i":"12102700700160","s":"Zsolt27,7","m":"A. ind. aor. sg. 3."},{"g":"ἡ","h":"a/az","x":"a, az (használata általában mint a magyarban, de eltérés is van); ὁ μέν... ὁ δέ...: az egyik... a másik...; ὁ δέ az pedig, ő pedig <br>m/f/n.sg.nom.: ὁ, ἡ, τό <br>m/f/n.sg.acc.: τόν, τήν, τό <br>m/f/n.sg.gen.: τοῦ, τῆς, τοῦ <br>m/f/n.sg.dat.: τῷ, τῇ, τῷ<br>m/f/n.pl.nom.: οἱ, αἱ, τά <br>m/f/n.pl.acc.: τούς, τάς, τά <br>m/f/n.pl.gen.: τῶν, τῶν, τῶν<br>m/f/n.pl.dat.: τοῖς, ταῖς, τοῖς","i":"12102700700170","s":"Zsolt27,7","m":"f. sg. nom."},{"g":"σάρξ","h":"hústest","x":"hús, test, (esetleg) hústest; <abbr class='literature'>BÚG</abbr>: κ tövű ragozás","i":"12102700700180","s":"Zsolt27,7","m":"f. sg. nom."},{"g":"μου·","h":"enyém","x":"én; Ragozása: <br>sg.1.nom.: ἐγώ (én; <abbr class='literature'>ÚSzSz</abbr>: 1473); <br>sg.1.acc.: ἐμέ v. μέ (engem; <abbr class='literature'>ÚSzSz</abbr>: 1691);<br>sg.1.gen.: ἐμού v. μού (enyém; <abbr class='literature'>ÚSzSz</abbr>: 1700); <br>sg.1.dat.: ἐμοί v. μοί (nekem; <abbr class='literature'>ÚSzSz</abbr>: 1698)","i":"12102700700190","s":"Zsolt27,7","m":"sg. 1. gen."},{"g":"καὶ","h":"és","x":"és, is","i":"12102700700200","s":"Zsolt27,7","m":""},{"g":"ἐκ","h":"-tól/-től","x":"-ból/-ből; -tól/-től; közül","i":"12102700700210","s":"Zsolt27,7","m":"+ gen."},{"g":"θελήματός","h":"öröm","x":"1. akarat 2. vágy, óhaj 3. öröm, gyönyörűség","i":"12102700700220","s":"Zsolt27,7","m":"n. sg. gen."},{"g":"μου","h":"enyém","x":"én; Ragozása: <br>sg.1.nom.: ἐγώ (én; <abbr class='literature'>ÚSzSz</abbr>: 1473); <br>sg.1.acc.: ἐμέ v. μέ (engem; <abbr class='literature'>ÚSzSz</abbr>: 1691);<br>sg.1.gen.: ἐμού v. μού (enyém; <abbr class='literature'>ÚSzSz</abbr>: 1700); <br>sg.1.dat.: ἐμοί v. μοί (nekem; <abbr class='literature'>ÚSzSz</abbr>: 1698)","i":"12102700700230","s":"Zsolt27,7","m":"sg. 1. gen."},{"g":"ἐξομολογήσομαι","h":"vallomást teszek majd","x":"megvall, hálát ad, dicsőít","i":"12102700700240","s":"Zsolt27,7","m":"M. fut. sg. 1."},{"g":"αὐτῷ.","h":"neki","x":"1) (pron.pers.) ő, ők (m/f/n.sg/pl.3. - neutrumban, pl. ha gyermekről van szó) 2) (pron.dem.) az, azok (n.sg/pl.3.) 3) (pron.refl.) téged magadat, temagadé, neked magadnak, őt magát, övé magáé, neki magának stb. (m/f.sg/pl.2/3.) vö: εἁυτοῦ, -ῆς, -οῦ (1438); 4) ὁ αὐτός: ugyanaz (pron.dem.)","i":"12102700700250","s":"Zsolt27,7","m":"m. sg. 3. dat."}]},{"w":[{"g":"κύριος κραταίωμα τοῦ λαοῦ αὐτοῦ καὶ ὑπερασπιστὴς τῶν σωτηρίων τοῦ χριστοῦ αὐτοῦ ἐστιν.","h":"Úr szilárdság a/az népé övé és támogató a/az megmentéseké a/az felkenté övé van","x":"úr; Úr - A Septuagintában legtöbbször a négybetűs Istennév, a Tetragrammaton <span lang='he'>יהוה</span> helyettesítője","i":"12102700800010","s":"Zsolt27,8","m":"m. sg. nom."},{"g":"κύριος","h":"Úr","x":"úr; Úr - A Septuagintában legtöbbször a négybetűs Istennév, a Tetragrammaton <span lang='he'>יהוה</span> helyettesítője","i":"12102700800010","s":"Zsolt27,8","m":"m. sg. nom."},{"g":"κραταίωμα","h":"szilárdság","x":"erő, szilárdság","i":"12102700800020","s":"Zsolt27,8","m":"n. sg. nom."},{"g":"τοῦ","h":"a/az","x":"a, az (használata általában mint a magyarban, de eltérés is van); ὁ μέν... ὁ δέ...: az egyik... a másik...; ὁ δέ az pedig, ő pedig <br>m/f/n.sg.nom.: ὁ, ἡ, τό <br>m/f/n.sg.acc.: τόν, τήν, τό <br>m/f/n.sg.gen.: τοῦ, τῆς, τοῦ <br>m/f/n.sg.dat.: τῷ, τῇ, τῷ<br>m/f/n.pl.nom.: οἱ, αἱ, τά <br>m/f/n.pl.acc.: τούς, τάς, τά <br>m/f/n.pl.gen.: τῶν, τῶν, τῶν<br>m/f/n.pl.dat.: τοῖς, ταῖς, τοῖς","i":"12102700800030","s":"Zsolt27,8","m":"m. sg. gen."},{"g":"λαοῦ","h":"népé","x":"nép","i":"12102700800040","s":"Zsolt27,8","m":"m. sg. gen."},{"g":"αὐτοῦ","h":"övé","x":"1) (pron.pers.) ő, ők (m/f/n.sg/pl.3. - neutrumban, pl. ha gyermekről van szó) 2) (pron.dem.) az, azok (n.sg/pl.3.) 3) (pron.refl.) téged magadat, temagadé, neked magadnak, őt magát, övé magáé, neki magának stb. (m/f.sg/pl.2/3.) vö: εἁυτοῦ, -ῆς, -οῦ (1438); 4) ὁ αὐτός: ugyanaz (pron.dem.)","i":"12102700800050","s":"Zsolt27,8","m":"m. sg. 3. gen."},{"g":"καὶ","h":"és","x":"és, is","i":"12102700800060","s":"Zsolt27,8","m":""},{"g":"ὑπερασπιστὴς","h":"támogató","x":"védelmező, támogató","i":"12102700800070","s":"Zsolt27,8","m":"m. sg. nom."},{"g":"τῶν","h":"a/az","x":"a, az (használata általában mint a magyarban, de eltérés is van); ὁ μέν... ὁ δέ...: az egyik... a másik...; ὁ δέ az pedig, ő pedig <br>m/f/n.sg.nom.: ὁ, ἡ, τό <br>m/f/n.sg.acc.: τόν, τήν, τό <br>m/f/n.sg.gen.: τοῦ, τῆς, τοῦ <br>m/f/n.sg.dat.: τῷ, τῇ, τῷ<br>m/f/n.pl.nom.: οἱ, αἱ, τά <br>m/f/n.pl.acc.: τούς, τάς, τά <br>m/f/n.pl.gen.: τῶν, τῶν, τῶν<br>m/f/n.pl.dat.: τοῖς, ταῖς, τοῖς","i":"12102700800080","s":"Zsolt27,8","m":"n. pl. gen."},{"g":"σωτηρίων","h":"megmentéseké","x":"üdvösség, megmentés, megőrzés","i":"12102700800090","s":"Zsolt27,8","m":"n. pl. gen."},{"g":"τοῦ","h":"a/az","x":"a, az (használata általában mint a magyarban, de eltérés is van); ὁ μέν... ὁ δέ...: az egyik... a másik...; ὁ δέ az pedig, ő pedig <br>m/f/n.sg.nom.: ὁ, ἡ, τό <br>m/f/n.sg.acc.: τόν, τήν, τό <br>m/f/n.sg.gen.: τοῦ, τῆς, τοῦ <br>m/f/n.sg.dat.: τῷ, τῇ, τῷ<br>m/f/n.pl.nom.: οἱ, αἱ, τά <br>m/f/n.pl.acc.: τούς, τάς, τά <br>m/f/n.pl.gen.: τῶν, τῶν, τῶν<br>m/f/n.pl.dat.: τοῖς, ταῖς, τοῖς","i":"12102700800100","s":"Zsolt27,8","m":"m. sg. gen."},{"g":"χριστοῦ","h":"felkenté","x":"fölkent, Krisztus; A szó Jézusra alkalmazva már tulajdonnévvé válik. Erre utal a névelő hiánya pl. a <a href='/text/Mk/1/1' class='ref' data-poload='/text/verse-text/Mk/1/1'>Mk 1,1</a>-ben. Eredetileg a héber <span lang='he'>מָשִׁיַח</span> = fölkent (Messiás) görög megfelelőjeként a felkenés által méltóságukba beiktatott személyek (király, pap) címe","i":"12102700800110","s":"Zsolt27,8","m":"m. sg. gen."},{"g":"αὐτοῦ","h":"övé","x":"1) (pron.pers.) ő, ők (m/f/n.sg/pl.3. - neutrumban, pl. ha gyermekről van szó) 2) (pron.dem.) az, azok (n.sg/pl.3.) 3) (pron.refl.) téged magadat, temagadé, neked magadnak, őt magát, övé magáé, neki magának stb. (m/f.sg/pl.2/3.) vö: εἁυτοῦ, -ῆς, -οῦ (1438); 4) ὁ αὐτός: ugyanaz (pron.dem.)","i":"12102700800120","s":"Zsolt27,8","m":"m. sg. 3. gen."},{"g":"ἐστιν.","h":"van","x":"van, jelen van (létige); ο?́ εστι: aki van; Ragozása: <br>A.praes.impf. (vagyok...): εἰμί, εἶ, ἐστί(ν), ἐσμέν, ἐστέ, εἰσί(ν);<br>A.praet.impf. (voltam...): ἤμην, ἦσθα, ἤν, ἦμεν v. ἤμεθα, ἦτε, ἦσαν;<br>A.coni.impf. (volnék...): ὦ, ἦς, ᾖ , ὦμεν, ἦτε, ὦσι(ν);<br>A.opt.impf. (bár lennék...): εἴην, εἴης, εἴη, εἴημεν v. εἶμεν, εἴητε v. εἶτε, εἴησαν v. εἶεν;<br>A.imprt.impf. (legyél!...): ἴσθι, ἔστω v. ἤτω, ἔσθε, ἔστωσαν v. ἤτωσαν;<br>A.part.impf.m/f/n.sg.nom. (levő): ὤν; οὖσα; ὄν;<br>A.inf.impf. (lenni): εἶναι;<br>M.fut. (leszek): ἔσομαι, ἔσῃ, ἔσται, ἐσόμεθα, ἔσεσθε, ἔσονατι;<br>M.inf.fut.(lenni majd): ἔσεσθαι;<br>M.part.fut.m/f/n.sg.nom (majd levő): ἐσόμενος; ἐσομένη; ἐσόμενον","i":"12102700800130","s":"Zsolt27,8","m":"A. praes. impf. sg. 3."}]},{"w":[{"g":"σῶσον τὸν λαόν σου καὶ εὐλόγησον τὴν κληρονομίαν σου καὶ ποίμανον αὐτοὺς καὶ ἔπαρον αὐτοὺς ἕως τοῦ αἰῶνος.","h":"szabadítsd meg a/az népet tiéd és áldd meg a/az örökséget tiéd és legeltesd őket és emeld fel őket -ig a/az örök","x":"megment, megszabadít; megtart; életben tart; üdvözít; σῴζω írásmód: <abbr class='literature'>GNT27</abbr>; σώζω írásmód: <abbr class='literature'>GNT_WH</abbr>","i":"12102700900010","s":"Zsolt27,9","m":"A. imprt. aor. sg. 2."},{"g":"σῶσον","h":"szabadítsd meg","x":"megment, megszabadít; megtart; életben tart; üdvözít; σῴζω írásmód: <abbr class='literature'>GNT27</abbr>; σώζω írásmód: <abbr class='literature'>GNT_WH</abbr>","i":"12102700900010","s":"Zsolt27,9","m":"A. imprt. aor. sg. 2."},{"g":"τὸν","h":"a/az","x":"a, az (használata általában mint a magyarban, de eltérés is van); ὁ μέν... ὁ δέ...: az egyik... a másik...; ὁ δέ az pedig, ő pedig <br>m/f/n.sg.nom.: ὁ, ἡ, τό <br>m/f/n.sg.acc.: τόν, τήν, τό <br>m/f/n.sg.gen.: τοῦ, τῆς, τοῦ <br>m/f/n.sg.dat.: τῷ, τῇ, τῷ<br>m/f/n.pl.nom.: οἱ, αἱ, τά <br>m/f/n.pl.acc.: τούς, τάς, τά <br>m/f/n.pl.gen.: τῶν, τῶν, τῶν<br>m/f/n.pl.dat.: τοῖς, ταῖς, τοῖς","i":"12102700900020","s":"Zsolt27,9","m":"m. sg. acc."},{"g":"λαόν","h":"népet","x":"nép","i":"12102700900030","s":"Zsolt27,9","m":"m. sg. acc."},{"g":"σου","h":"tiéd","x":"te; Ragozása:<br>sg.2.nom.: σύ (te)<br>sg.2.acc.: σέ v. σε (téged) <br>sg.2.gen.: σοῦ v. σου (tiéd)<br>sg.2.dat.: σοί v. σοι (neked)","i":"12102700900040","s":"Zsolt27,9","m":"sg. 2. gen."},{"g":"καὶ","h":"és","x":"és, is","i":"12102700900050","s":"Zsolt27,9","m":""},{"g":"εὐλόγησον","h":"áldd meg","x":"(meg)áld","i":"12102700900060","s":"Zsolt27,9","m":"A. imprt. aor. sg. 2."},{"g":"τὴν","h":"a/az","x":"a, az (használata általában mint a magyarban, de eltérés is van); ὁ μέν... ὁ δέ...: az egyik... a másik...; ὁ δέ az pedig, ő pedig <br>m/f/n.sg.nom.: ὁ, ἡ, τό <br>m/f/n.sg.acc.: τόν, τήν, τό <br>m/f/n.sg.gen.: τοῦ, τῆς, τοῦ <br>m/f/n.sg.dat.: τῷ, τῇ, τῷ<br>m/f/n.pl.nom.: οἱ, αἱ, τά <br>m/f/n.pl.acc.: τούς, τάς, τά <br>m/f/n.pl.gen.: τῶν, τῶν, τῶν<br>m/f/n.pl.dat.: τοῖς, ταῖς, τοῖς","i":"12102700900070","s":"Zsolt27,9","m":"f. sg. acc."},{"g":"κληρονομίαν","h":"örökséget","x":"örökség","i":"12102700900080","s":"Zsolt27,9","m":"f. sg. acc."},{"g":"σου","h":"tiéd","x":"te; Ragozása:<br>sg.2.nom.: σύ (te)<br>sg.2.acc.: σέ v. σε (téged) <br>sg.2.gen.: σοῦ v. σου (tiéd)<br>sg.2.dat.: σοί v. σοι (neked)","i":"12102700900090","s":"Zsolt27,9","m":"sg. 2. gen."},{"g":"καὶ","h":"és","x":"és, is","i":"12102700900100","s":"Zsolt27,9","m":""},{"g":"ποίμανον","h":"legeltesd","x":"legeltet, pásztorol","i":"12102700900110","s":"Zsolt27,9","m":"A. imprt. aor. sg. 2."},{"g":"αὐτοὺς","h":"őket","x":"1) (pron.pers.) ő, ők (m/f/n.sg/pl.3. - neutrumban, pl. ha gyermekről van szó) 2) (pron.dem.) az, azok (n.sg/pl.3.) 3) (pron.refl.) téged magadat, temagadé, neked magadnak, őt magát, övé magáé, neki magának stb. (m/f.sg/pl.2/3.) vö: εἁυτοῦ, -ῆς, -οῦ (1438); 4) ὁ αὐτός: ugyanaz (pron.dem.)","i":"12102700900120","s":"Zsolt27,9","m":"m. pl. 3. acc."},{"g":"καὶ","h":"és","x":"és, is","i":"12102700900130","s":"Zsolt27,9","m":""},{"g":"ἔπαρον","h":"emeld fel","x":"1) felemel; 2) (gőggel) felfuvalkodik","i":"12102700900140","s":"Zsolt27,9","m":"A. imprt. aor. sg. 2."},{"g":"αὐτοὺς","h":"őket","x":"1) (pron.pers.) ő, ők (m/f/n.sg/pl.3. - neutrumban, pl. ha gyermekről van szó) 2) (pron.dem.) az, azok (n.sg/pl.3.) 3) (pron.refl.) téged magadat, temagadé, neked magadnak, őt magát, övé magáé, neki magának stb. (m/f.sg/pl.2/3.) vö: εἁυτοῦ, -ῆς, -οῦ (1438); 4) ὁ αὐτός: ugyanaz (pron.dem.)","i":"12102700900150","s":"Zsolt27,9","m":"m. pl. 3. acc."},{"g":"ἕως","h":"-ig","x":"1. (coni.) amíg; 2. (praep.) -ig, amíg (időben és néha térben)","i":"12102700900160","s":"Zsolt27,9","m":"+ gen."},{"g":"τοῦ","h":"a/az","x":"a, az (használata általában mint a magyarban, de eltérés is van); ὁ μέν... ὁ δέ...: az egyik... a másik...; ὁ δέ az pedig, ő pedig <br>m/f/n.sg.nom.: ὁ, ἡ, τό <br>m/f/n.sg.acc.: τόν, τήν, τό <br>m/f/n.sg.gen.: τοῦ, τῆς, τοῦ <br>m/f/n.sg.dat.: τῷ, τῇ, τῷ<br>m/f/n.pl.nom.: οἱ, αἱ, τά <br>m/f/n.pl.acc.: τούς, τάς, τά <br>m/f/n.pl.gen.: τῶν, τῶν, τῶν<br>m/f/n.pl.dat.: τοῖς, ταῖς, τοῖς","i":"12102700900170","s":"Zsolt27,9","m":"m. sg. gen."},{"g":"αἰῶνος.","h":"örök","x":"1. korszak; 2. beláthatatlan idő; 3. örökkévalóság","i":"12102700900180","s":"Zsolt27,9","m":"m. sg. gen."}]}]}